{
  "appgroup_id": "6a031f6de47a78f5e7981e0c",
  "appgroup_name": "Reisebüro-Buchungssystem",
  "apps": {
    "reisepakete": {
      "app_id": "6a031f4c161bbeec8df93d84",
      "name": "Reisepakete",
      "main": false,
      "controls": {
        "paket_name": {
          "identifier": "paket_name",
          "label": "Name des Reisepakets",
          "type": "string",
          "subtype": "text",
          "fulltype": "string/text",
          "description": "A string value not longer than 4000 characters (or `null`/`None`).",
          "required": null,
          "in_list": true,
          "in_mobile_list": true,
          "in_text": true,
          "in_structured_search": false,
          "in_fulltext_search": true,
          "in_expert_search": true
        },
        "zielort": {
          "identifier": "zielort",
          "label": "Zielort",
          "type": "string",
          "subtype": "text",
          "fulltype": "string/text",
          "description": "A string value not longer than 4000 characters (or `null`/`None`).",
          "required": null,
          "in_list": true,
          "in_mobile_list": true,
          "in_text": true,
          "in_structured_search": false,
          "in_fulltext_search": true,
          "in_expert_search": true
        },
        "basispreis_erwachsener": {
          "identifier": "basispreis_erwachsener",
          "label": "Basispreis pro Erwachsenem (€)",
          "type": "number",
          "subtype": null,
          "fulltype": "number",
          "description": "A decimal number value (or `null`/`None`).",
          "required": null,
          "in_list": true,
          "in_mobile_list": false,
          "in_text": false,
          "in_structured_search": false,
          "in_fulltext_search": true,
          "in_expert_search": true,
          "precision": null
        },
        "kinder_faktor": {
          "identifier": "kinder_faktor",
          "label": "Kinder-Faktor (0.5–1.0)",
          "type": "number",
          "subtype": null,
          "fulltype": "number",
          "description": "A decimal number value (or `null`/`None`).",
          "required": null,
          "in_list": true,
          "in_mobile_list": false,
          "in_text": false,
          "in_structured_search": false,
          "in_fulltext_search": true,
          "in_expert_search": true,
          "precision": null
        },
        "mindestteilnehmer": {
          "identifier": "mindestteilnehmer",
          "label": "Mindestteilnehmer",
          "type": "number",
          "subtype": null,
          "fulltype": "number",
          "description": "A decimal number value (or `null`/`None`).",
          "required": null,
          "in_list": true,
          "in_mobile_list": false,
          "in_text": false,
          "in_structured_search": false,
          "in_fulltext_search": true,
          "in_expert_search": true,
          "precision": null
        }
      }
    },
    "unterkuenfte": {
      "app_id": "6a031f5397966ce6d6355a09",
      "name": "Unterkünfte",
      "main": false,
      "controls": {
        "hotelname": {
          "identifier": "hotelname",
          "label": "Hotelname",
          "type": "string",
          "subtype": "text",
          "fulltype": "string/text",
          "description": "A string value not longer than 4000 characters (or `null`/`None`).",
          "required": null,
          "in_list": true,
          "in_mobile_list": true,
          "in_text": true,
          "in_structured_search": false,
          "in_fulltext_search": true,
          "in_expert_search": true
        },
        "sterne": {
          "identifier": "sterne",
          "label": "Sterne (1–5)",
          "type": "number",
          "subtype": null,
          "fulltype": "number",
          "description": "A decimal number value (or `null`/`None`).",
          "required": null,
          "in_list": true,
          "in_mobile_list": true,
          "in_text": true,
          "in_structured_search": false,
          "in_fulltext_search": true,
          "in_expert_search": true,
          "precision": null
        },
        "preis_pro_nacht": {
          "identifier": "preis_pro_nacht",
          "label": "Preis pro Nacht (€)",
          "type": "number",
          "subtype": null,
          "fulltype": "number",
          "description": "A decimal number value (or `null`/`None`).",
          "required": null,
          "in_list": true,
          "in_mobile_list": false,
          "in_text": false,
          "in_structured_search": false,
          "in_fulltext_search": true,
          "in_expert_search": true,
          "precision": null
        },
        "kurtaxe_pro_person_nacht": {
          "identifier": "kurtaxe_pro_person_nacht",
          "label": "Kurtaxe pro Person/Nacht (€)",
          "type": "number",
          "subtype": null,
          "fulltype": "number",
          "description": "A decimal number value (or `null`/`None`).",
          "required": null,
          "in_list": true,
          "in_mobile_list": false,
          "in_text": false,
          "in_structured_search": false,
          "in_fulltext_search": true,
          "in_expert_search": true,
          "precision": null
        }
      }
    },
    "ausfluege": {
      "app_id": "6a031f53b08cd498187c08c5",
      "name": "Ausflüge",
      "main": false,
      "controls": {
        "ausflug_name": {
          "identifier": "ausflug_name",
          "label": "Name des Ausflugs",
          "type": "string",
          "subtype": "text",
          "fulltype": "string/text",
          "description": "A string value not longer than 4000 characters (or `null`/`None`).",
          "required": null,
          "in_list": true,
          "in_mobile_list": true,
          "in_text": true,
          "in_structured_search": false,
          "in_fulltext_search": true,
          "in_expert_search": true
        },
        "preis_pro_person": {
          "identifier": "preis_pro_person",
          "label": "Preis pro Person (€)",
          "type": "number",
          "subtype": null,
          "fulltype": "number",
          "description": "A decimal number value (or `null`/`None`).",
          "required": null,
          "in_list": true,
          "in_mobile_list": true,
          "in_text": true,
          "in_structured_search": false,
          "in_fulltext_search": true,
          "in_expert_search": true,
          "precision": null
        },
        "dauer_stunden": {
          "identifier": "dauer_stunden",
          "label": "Dauer (Stunden)",
          "type": "number",
          "subtype": null,
          "fulltype": "number",
          "description": "A decimal number value (or `null`/`None`).",
          "required": null,
          "in_list": true,
          "in_mobile_list": false,
          "in_text": false,
          "in_structured_search": false,
          "in_fulltext_search": true,
          "in_expert_search": true,
          "precision": null
        }
      }
    },
    "reisebuchung": {
      "app_id": "6a031f549b19e27808c3cc43",
      "name": "Reisebuchung",
      "main": false,
      "controls": {
        "kunde_vorname": {
          "identifier": "kunde_vorname",
          "label": "Vorname des Kunden",
          "type": "string",
          "subtype": "text",
          "fulltype": "string/text",
          "description": "A string value not longer than 4000 characters (or `null`/`None`).",
          "required": null,
          "in_list": true,
          "in_mobile_list": true,
          "in_text": true,
          "in_structured_search": false,
          "in_fulltext_search": true,
          "in_expert_search": true
        },
        "kunde_nachname": {
          "identifier": "kunde_nachname",
          "label": "Nachname des Kunden",
          "type": "string",
          "subtype": "text",
          "fulltype": "string/text",
          "description": "A string value not longer than 4000 characters (or `null`/`None`).",
          "required": null,
          "in_list": true,
          "in_mobile_list": true,
          "in_text": true,
          "in_structured_search": false,
          "in_fulltext_search": true,
          "in_expert_search": true
        },
        "buchungsdatum": {
          "identifier": "buchungsdatum",
          "label": "Buchungsdatum",
          "type": "date",
          "subtype": "date",
          "fulltype": "date/date",
          "description": "A calendar date consisting of year, month and day (or `null`/`None`)\n\nThe field value will be a string in the format `<YYYY>-<MM>-<DD>` (or `null`/`None`).\n\nFor example: `2000-02-29`.\n\nFor `POST`/`PUT`/`PATCH` requests the REST API uses a liberal parsing approach so that strings like `2026`, `February 29, 2000 12:34 MEST`, `letztes Jahr` etc. will be accepted as value date values. However this runs the risk of parsing ambiguous values incorrectly. To ensure reliable parsing it is best to use the canonical format specified above.",
          "required": null,
          "in_list": true,
          "in_mobile_list": false,
          "in_text": false,
          "in_structured_search": false,
          "in_fulltext_search": true,
          "in_expert_search": true
        },
        "reisepaket": {
          "identifier": "reisepaket",
          "label": "Reisepaket",
          "type": "applookup",
          "subtype": "select",
          "fulltype": "applookup/select",
          "description": "A reference to a LivingApp record from the target lookup app 'Reisepakete' with the id `6a031f4c161bbeec8df93d84` (or `null`/`None`).\n\nThe field value will be a valid record URL in the form `https://my.living-apps.de/rest/apps/6a031f4c161bbeec8df93d84/<record-id>` (or `null`/`None`).\n\nDisplayed as single-select field in HTML pages.",
          "required": null,
          "in_list": true,
          "in_mobile_list": false,
          "in_text": false,
          "in_structured_search": false,
          "in_fulltext_search": true,
          "in_expert_search": true,
          "lookup_app": "https://my.living-apps.de/rest/apps/6a031f4c161bbeec8df93d84"
        },
        "unterkunft": {
          "identifier": "unterkunft",
          "label": "Unterkunft",
          "type": "applookup",
          "subtype": "select",
          "fulltype": "applookup/select",
          "description": "A reference to a LivingApp record from the target lookup app 'Unterkünfte' with the id `6a031f5397966ce6d6355a09` (or `null`/`None`).\n\nThe field value will be a valid record URL in the form `https://my.living-apps.de/rest/apps/6a031f5397966ce6d6355a09/<record-id>` (or `null`/`None`).\n\nDisplayed as single-select field in HTML pages.",
          "required": null,
          "in_list": true,
          "in_mobile_list": false,
          "in_text": false,
          "in_structured_search": false,
          "in_fulltext_search": true,
          "in_expert_search": true,
          "lookup_app": "https://my.living-apps.de/rest/apps/6a031f5397966ce6d6355a09"
        },
        "anzahl_erwachsene": {
          "identifier": "anzahl_erwachsene",
          "label": "Anzahl Erwachsene",
          "type": "number",
          "subtype": null,
          "fulltype": "number",
          "description": "A decimal number value (or `null`/`None`).",
          "required": null,
          "in_list": false,
          "in_mobile_list": false,
          "in_text": false,
          "in_structured_search": false,
          "in_fulltext_search": null,
          "in_expert_search": true,
          "precision": null
        },
        "anzahl_kinder": {
          "identifier": "anzahl_kinder",
          "label": "Anzahl Kinder",
          "type": "number",
          "subtype": null,
          "fulltype": "number",
          "description": "A decimal number value (or `null`/`None`).",
          "required": null,
          "in_list": false,
          "in_mobile_list": false,
          "in_text": false,
          "in_structured_search": false,
          "in_fulltext_search": null,
          "in_expert_search": true,
          "precision": null
        },
        "abreisedatum": {
          "identifier": "abreisedatum",
          "label": "Abreisedatum",
          "type": "date",
          "subtype": "date",
          "fulltype": "date/date",
          "description": "A calendar date consisting of year, month and day (or `null`/`None`)\n\nThe field value will be a string in the format `<YYYY>-<MM>-<DD>` (or `null`/`None`).\n\nFor example: `2000-02-29`.\n\nFor `POST`/`PUT`/`PATCH` requests the REST API uses a liberal parsing approach so that strings like `2026`, `February 29, 2000 12:34 MEST`, `letztes Jahr` etc. will be accepted as value date values. However this runs the risk of parsing ambiguous values incorrectly. To ensure reliable parsing it is best to use the canonical format specified above.",
          "required": null,
          "in_list": false,
          "in_mobile_list": false,
          "in_text": false,
          "in_structured_search": false,
          "in_fulltext_search": null,
          "in_expert_search": true
        },
        "rueckreisedatum": {
          "identifier": "rueckreisedatum",
          "label": "Rückreisedatum",
          "type": "date",
          "subtype": "date",
          "fulltype": "date/date",
          "description": "A calendar date consisting of year, month and day (or `null`/`None`)\n\nThe field value will be a string in the format `<YYYY>-<MM>-<DD>` (or `null`/`None`).\n\nFor example: `2000-02-29`.\n\nFor `POST`/`PUT`/`PATCH` requests the REST API uses a liberal parsing approach so that strings like `2026`, `February 29, 2000 12:34 MEST`, `letztes Jahr` etc. will be accepted as value date values. However this runs the risk of parsing ambiguous values incorrectly. To ensure reliable parsing it is best to use the canonical format specified above.",
          "required": null,
          "in_list": false,
          "in_mobile_list": false,
          "in_text": false,
          "in_structured_search": false,
          "in_fulltext_search": null,
          "in_expert_search": true
        },
        "reisedauer_naechte": {
          "identifier": "reisedauer_naechte",
          "label": "Reisedauer (Nächte)",
          "type": "number",
          "subtype": null,
          "fulltype": "number",
          "description": "A decimal number value (or `null`/`None`).",
          "required": null,
          "in_list": false,
          "in_mobile_list": false,
          "in_text": false,
          "in_structured_search": false,
          "in_fulltext_search": null,
          "in_expert_search": true,
          "precision": null
        },
        "verpflegung": {
          "identifier": "verpflegung",
          "label": "Verpflegung",
          "type": "lookup",
          "subtype": "radio",
          "fulltype": "lookup/radio",
          "description": "One selected option of multiple available options (or `null`/`None`).\n\nThe available options are defined in the `lookup_data` attribute of this control.\n\nThe field value will be the key in this `lookup_data` attribute (or `null`/`None`).\n\nDisplayed as radio button fields in HTML pages.",
          "required": null,
          "in_list": false,
          "in_mobile_list": false,
          "in_text": false,
          "in_structured_search": false,
          "in_fulltext_search": null,
          "in_expert_search": true,
          "lookup_data": {
            "ohne": "Ohne",
            "fruehstueck": "Frühstück",
            "halbpension": "Halbpension",
            "vollpension": "Vollpension"
          }
        },
        "reiseruecktrittsversicherung": {
          "identifier": "reiseruecktrittsversicherung",
          "label": "Reiserücktrittsversicherung",
          "type": "bool",
          "subtype": null,
          "fulltype": "bool",
          "description": "A boolean value, i.e. `true` or `false` (or `null`/`None`).",
          "required": null,
          "in_list": false,
          "in_mobile_list": false,
          "in_text": false,
          "in_structured_search": false,
          "in_fulltext_search": null,
          "in_expert_search": true
        },
        "zusatzausfluege": {
          "identifier": "zusatzausfluege",
          "label": "Zusatzausflüge",
          "type": "applookup",
          "subtype": "select",
          "fulltype": "applookup/select",
          "description": "A reference to a LivingApp record from the target lookup app 'Ausflüge' with the id `6a031f53b08cd498187c08c5` (or `null`/`None`).\n\nThe field value will be a valid record URL in the form `https://my.living-apps.de/rest/apps/6a031f53b08cd498187c08c5/<record-id>` (or `null`/`None`).\n\nDisplayed as single-select field in HTML pages.",
          "required": null,
          "in_list": false,
          "in_mobile_list": false,
          "in_text": false,
          "in_structured_search": false,
          "in_fulltext_search": null,
          "in_expert_search": true,
          "lookup_app": "https://my.living-apps.de/rest/apps/6a031f53b08cd498187c08c5"
        },
        "paketpreis_erwachsene": {
          "identifier": "paketpreis_erwachsene",
          "label": "Paketpreis Erwachsene (€)",
          "type": "number",
          "subtype": null,
          "fulltype": "number",
          "description": "A decimal number value (or `null`/`None`).",
          "required": null,
          "in_list": false,
          "in_mobile_list": false,
          "in_text": false,
          "in_structured_search": false,
          "in_fulltext_search": null,
          "in_expert_search": true,
          "precision": null
        },
        "paketpreis_kinder": {
          "identifier": "paketpreis_kinder",
          "label": "Paketpreis Kinder (€)",
          "type": "number",
          "subtype": null,
          "fulltype": "number",
          "description": "A decimal number value (or `null`/`None`).",
          "required": null,
          "in_list": false,
          "in_mobile_list": false,
          "in_text": false,
          "in_structured_search": false,
          "in_fulltext_search": null,
          "in_expert_search": true,
          "precision": null
        },
        "unterkunftskosten": {
          "identifier": "unterkunftskosten",
          "label": "Unterkunftskosten (€)",
          "type": "number",
          "subtype": null,
          "fulltype": "number",
          "description": "A decimal number value (or `null`/`None`).",
          "required": null,
          "in_list": false,
          "in_mobile_list": false,
          "in_text": false,
          "in_structured_search": false,
          "in_fulltext_search": null,
          "in_expert_search": true,
          "precision": null
        },
        "verpflegungskosten": {
          "identifier": "verpflegungskosten",
          "label": "Verpflegungskosten (€)",
          "type": "number",
          "subtype": null,
          "fulltype": "number",
          "description": "A decimal number value (or `null`/`None`).",
          "required": null,
          "in_list": false,
          "in_mobile_list": false,
          "in_text": false,
          "in_structured_search": false,
          "in_fulltext_search": null,
          "in_expert_search": true,
          "precision": null
        },
        "kurtaxe": {
          "identifier": "kurtaxe",
          "label": "Kurtaxe (€)",
          "type": "number",
          "subtype": null,
          "fulltype": "number",
          "description": "A decimal number value (or `null`/`None`).",
          "required": null,
          "in_list": false,
          "in_mobile_list": false,
          "in_text": false,
          "in_structured_search": false,
          "in_fulltext_search": null,
          "in_expert_search": true,
          "precision": null
        },
        "ausfluege_summe": {
          "identifier": "ausfluege_summe",
          "label": "Ausflüge Summe (€)",
          "type": "number",
          "subtype": null,
          "fulltype": "number",
          "description": "A decimal number value (or `null`/`None`).",
          "required": null,
          "in_list": false,
          "in_mobile_list": false,
          "in_text": false,
          "in_structured_search": false,
          "in_fulltext_search": null,
          "in_expert_search": true,
          "precision": null
        },
        "versicherungskosten": {
          "identifier": "versicherungskosten",
          "label": "Versicherungskosten (€)",
          "type": "number",
          "subtype": null,
          "fulltype": "number",
          "description": "A decimal number value (or `null`/`None`).",
          "required": null,
          "in_list": false,
          "in_mobile_list": false,
          "in_text": false,
          "in_structured_search": false,
          "in_fulltext_search": null,
          "in_expert_search": true,
          "precision": null
        },
        "fruehbucher_rabatt": {
          "identifier": "fruehbucher_rabatt",
          "label": "Frühbucher-Rabatt (€)",
          "type": "number",
          "subtype": null,
          "fulltype": "number",
          "description": "A decimal number value (or `null`/`None`).",
          "required": null,
          "in_list": false,
          "in_mobile_list": false,
          "in_text": false,
          "in_structured_search": false,
          "in_fulltext_search": null,
          "in_expert_search": true,
          "precision": null
        },
        "netto_gesamt": {
          "identifier": "netto_gesamt",
          "label": "Netto Gesamt (€)",
          "type": "number",
          "subtype": null,
          "fulltype": "number",
          "description": "A decimal number value (or `null`/`None`).",
          "required": null,
          "in_list": false,
          "in_mobile_list": false,
          "in_text": false,
          "in_structured_search": false,
          "in_fulltext_search": null,
          "in_expert_search": true,
          "precision": null
        },
        "mwst_betrag": {
          "identifier": "mwst_betrag",
          "label": "MwSt-Betrag (€)",
          "type": "number",
          "subtype": null,
          "fulltype": "number",
          "description": "A decimal number value (or `null`/`None`).",
          "required": null,
          "in_list": false,
          "in_mobile_list": false,
          "in_text": false,
          "in_structured_search": false,
          "in_fulltext_search": null,
          "in_expert_search": true,
          "precision": null
        },
        "brutto_gesamt": {
          "identifier": "brutto_gesamt",
          "label": "Brutto Gesamt (€)",
          "type": "number",
          "subtype": null,
          "fulltype": "number",
          "description": "A decimal number value (or `null`/`None`).",
          "required": null,
          "in_list": false,
          "in_mobile_list": false,
          "in_text": false,
          "in_structured_search": false,
          "in_fulltext_search": null,
          "in_expert_search": true,
          "precision": null
        },
        "anzahlung": {
          "identifier": "anzahlung",
          "label": "Anzahlung (€, 20% von Brutto)",
          "type": "number",
          "subtype": null,
          "fulltype": "number",
          "description": "A decimal number value (or `null`/`None`).",
          "required": null,
          "in_list": false,
          "in_mobile_list": false,
          "in_text": false,
          "in_structured_search": false,
          "in_fulltext_search": null,
          "in_expert_search": true,
          "precision": null
        }
      }
    }
  },
  "metadata": {
    "apps_list": [
      "Reisepakete",
      "Unterkünfte",
      "Ausflüge",
      "Reisebuchung"
    ]
  }
}